gadopenapiconverter/__init__.py
gadopenapiconverter/cli.py
gadopenapiconverter/const/__init__.py
gadopenapiconverter/const/extentions.py
gadopenapiconverter/const/files.py
gadopenapiconverter/const/http.py
gadopenapiconverter/const/models.py
gadopenapiconverter/const/regexp.py
gadopenapiconverter/const/specification.py
gadopenapiconverter/const/symbols.py
gadopenapiconverter/const/syntax.py
gadopenapiconverter/const/templates.py
gadopenapiconverter/enums/__init__.py
gadopenapiconverter/enums/http.py
gadopenapiconverter/enums/python.py
gadopenapiconverter/enums/specification.py
gadopenapiconverter/enums/typing.py
gadopenapiconverter/mappers/__init__.py
gadopenapiconverter/mappers/python.py
gadopenapiconverter/mappers/specification.py
gadopenapiconverter/models/__init__.py
gadopenapiconverter/models/fields.py
gadopenapiconverter/models/http.py
gadopenapiconverter/models/python.py
gadopenapiconverter/models/specification.py
gadopenapiconverter/os/__init__.py
gadopenapiconverter/os/files.py
gadopenapiconverter/os/folders.py
gadopenapiconverter/os/http.py
gadopenapiconverter/parsers/__init__.py
gadopenapiconverter/parsers/specification.py
gadopenapiconverter/typings/__init__.py
gadopenapiconverter/typings/abc.py
gadopenapiconverter/typings/enums.py
gadopenapiconverter/typings/typing.py
gadopenapiconverter/utils/__init__.py
gadopenapiconverter/utils/codegeneration.py
gadopenapiconverter/utils/files.py
gadopenapiconverter/utils/specification.py
gadopenapiconverter/utils/toml.py
tests/__init__.py
tests/test_init.py
gadopenapiconverter-0.0.2.dist-info/LICENSE
gadopenapiconverter-0.0.2.dist-info/METADATA
gadopenapiconverter-0.0.2.dist-info/WHEEL
gadopenapiconverter-0.0.2.dist-info/entry_points.txt
gadopenapiconverter-0.0.2.dist-info/top_level.txt
gadopenapiconverter-0.0.2.dist-info/RECORD
